[{"id":"fdc6c164-6bda-4338-a042-c402a455553b","description":"Test","dateDebut":1715277733519,"dateFin":1715277733519,"note":"123","id_project":"123","documentIds":[],"closed":false},{"id":"8a7b48c4-829b-4d48-8ace-b0d3e967ddf7","description":"Test","dateDebut":1715277848484,"dateFin":1715277848484,"note":"123","id_project":"123","documentIds":[],"closed":false},{"id":"8e2dc445-4378-4c55-b890-d9896527bbb5","description":"Test","dateDebut":1715278054941,"dateFin":1715278054941,"note":"123","id_project":"123","documentIds":[],"closed":false},{"id":"7ae0d557-e7de-4df7-aaa4-81412666d5dd","description":"Test","dateDebut":1715278251946,"dateFin":1715278251946,"note":"123","id_project":"123","documentIds":[],"closed":false},{"id":"3eacdf16-7d82-46ee-9513-83dcf1609e34","description":"Test","dateDebut":1715278282360,"dateFin":1715278282360,"note":"123","id_project":"123","documentIds":[],"closed":false},{"id":"823a7a9e-dcdc-4cd4-8f31-a0a6874a06ca","description":"Test","dateDebut":1715278301293,"dateFin":1715278301293,"note":"123","id_project":"123","documentIds":[],"closed":false},{"id":"94e49178-803b-490c-b57a-29b6393aa4e4","description":"Test","dateDebut":1715278442916,"dateFin":1715278442916,"note":"123","id_project":"123","documentIds":[],"closed":false},{"id":"1da969c9-4299-41b1-a52a-d6a847e453fd","description":"Test","dateDebut":1715278508309,"dateFin":1715278508309,"note":"123","id_project":"123","documentIds":["123"],"closed":false},{"id":"53d24c4e-0423-463e-9ab3-23243cae1472","description":"Test","dateDebut":1715278629126,"dateFin":1715278629126,"note":"123","id_project":"123","documentIds":["123"],"closed":false},{"id":"8493ec9c-b770-4d10-a866-772130492754","description":"Test","dateDebut":1715278714170,"dateFin":1715278714170,"note":"123","id_project":"123","documentIds":["3b915a8c-b087-4774-bdfa-ca1c89c37bdf"],"closed":false},{"id":"b58c84dd-59da-4ec4-86c4-c3aebf6da5e8","description":"Test","dateDebut":1715279392034,"dateFin":1715279392034,"note":"123","id_project":"123","documentIds":["3b915a8c-b087-4774-bdfa-ca1c89c37bdf"],"closed":false},{"id":"3b25c7aa-877b-462b-b49c-a14b9dcc4f29","description":"Test","dateDebut":1715279562443,"dateFin":1715279562443,"note":"123","id_project":"123","documentIds":["3b915a8c-b087-4774-bdfa-ca1c89c37bdf"],"closed":false},{"id":"acd309a1-c7b1-43f1-aafb-21140b95b717","description":"Test","dateDebut":1715279658364,"dateFin":1715279658364,"note":"123","id_project":"123","documentIds":["3b915a8c-b087-4774-bdfa-ca1c89c37bdf"],"closed":false},{"id":"577e9e0c-0680-41ae-9054-efe116390098","description":"Test","dateDebut":1715279781666,"dateFin":1715279781667,"note":"123","id_project":"123","documentIds":["3b915a8c-b087-4774-bdfa-ca1c89c37bdf"],"closed":false}]